ckanext/__init__.py
ckanext/twitter/__init__.py
ckanext/twitter/plugin.py
ckanext/twitter/lib/__init__.py
ckanext/twitter/lib/cache_helpers.py
ckanext/twitter/lib/config_helpers.py
ckanext/twitter/lib/helpers.py
ckanext/twitter/lib/parsers.py
ckanext/twitter/lib/twitter_api.py
ckanext/twitter/routes/__init__.py
ckanext/twitter/routes/tweet.py
ckanext/twitter/theme/assets/webassets.yml
ckanext/twitter/theme/assets/scripts/modules/confirm-tweet.js
ckanext/twitter/theme/templates/ajax_snippets/edit_tweet.html
ckanext/twitter/theme/templates/package/base.html
ckanext/twitter/theme/templates/package/read_base.html
docs/_scripts/gen_api_pages.py
ckanext_twitter-2.2.9.dist-info/LICENSE
ckanext_twitter-2.2.9.dist-info/METADATA
ckanext_twitter-2.2.9.dist-info/WHEEL
ckanext_twitter-2.2.9.dist-info/entry_points.txt
ckanext_twitter-2.2.9.dist-info/top_level.txt
ckanext_twitter-2.2.9.dist-info/RECORD
